easyansi/__init__.py
easyansi/colorpacks/__init__.py
easyansi/colorpacks/hello.py
easy_ansi_color_packs-0.0.0a1.dist-info/LICENSE
easy_ansi_color_packs-0.0.0a1.dist-info/METADATA
easy_ansi_color_packs-0.0.0a1.dist-info/WHEEL
easy_ansi_color_packs-0.0.0a1.dist-info/top_level.txt
easy_ansi_color_packs-0.0.0a1.dist-info/RECORD
